giftbit/__init__.py
giftbit/exceptions.py
giftbit/api/__init__.py
giftbit/api/base.py
giftbit/api/brands.py
giftbit/api/campaign.py
giftbit/api/embedded.py
giftbit/api/funds.py
giftbit/api/gifts.py
giftbit/api/ping.py
giftbit/api/regions.py
giftbit_api-0.2.1.dist-info/LICENSE
giftbit_api-0.2.1.dist-info/METADATA
giftbit_api-0.2.1.dist-info/WHEEL
giftbit_api-0.2.1.dist-info/top_level.txt
giftbit_api-0.2.1.dist-info/RECORD
